{
    "ret": true,
    "data":{
        "hotCities": [{
            "id": 1,
            "spell": "beijing",
            "name": "北京"
          },{
              "id": 2,
              "spell":"shaghai",
              "name": "上海"
          },{
              "id": 3,
              "spell": "guangzhou",
              "name": "广州"
          },{
              "id": 4,
              "spell": "hefei",
              "name": "合肥"
          },{
              "id": 5,
              "spell": "huaibei",
              "name": "淮北"
          }
        ],
        "sort": [
            {
                "id": 1,
                "key": "H",
                "name": "合肥"
            }
        ]
    }    
}